ead/__init__.py
ead/apps.py
ead/constants.py
ead/models.py
ead/serialisers.py
ead/urls.py
ead/validators.py
ead/management/commands/ead-to-html.xsl
ead/management/commands/ead3.xsd
ead/management/commands/html-to-ead.xsl
ead/management/commands/import_ead_xml.py
ead/migrations/0001_initial.py
ead/migrations/__init__.py
ead/test_utils/__init__.py
ead/test_utils/test_app/__init__.py
django_ead-0.8.1.dist-info/AUTHORS.rst
django_ead-0.8.1.dist-info/LICENSE
django_ead-0.8.1.dist-info/METADATA
django_ead-0.8.1.dist-info/WHEEL
django_ead-0.8.1.dist-info/top_level.txt
django_ead-0.8.1.dist-info/RECORD
