Metadata-Version: 2.1
Name: django-ead
Version: 0.8.1
Summary: Django app supporting EAD3 data import, editing, and XML serialisation.
Home-page: https://github.com/kingsdigitallab/autharch-base
Author: Jamie Norrish
Author-email: jamie@artefact.org.nz
License: MIT
Keywords: django-ead
Platform: UNKNOWN
Classifier: Development Status :: 3 - Alpha
Classifier: Framework :: Django :: 2.1
Classifier: Intended Audience :: Developers
Classifier: License :: OSI Approved :: BSD License
Classifier: Natural Language :: English
Classifier: Programming Language :: Python :: 2
Classifier: Programming Language :: Python :: 2.7
Classifier: Programming Language :: Python :: 3
Classifier: Programming Language :: Python :: 3.5
Classifier: Programming Language :: Python :: 3.6
Requires-Dist: django-controlled-vocabulary (>=0.10)
Requires-Dist: django-model-utils (>=2.0)
Requires-Dist: django-reversion
Requires-Dist: lxml (>=4.5.2)
